{
  "dataList": [
    {
      "id": 0,
      "place": "4-й Район – филиал Корпорации L",
      "model": "로쟈",
      "content": "Здесь всё кишит личинками."
    },
    {
      "id": 1,
      "model": "단테",
      "content": "<Хотя по сравнению с Аномалиями на предыдущих этажах, могло быть и хуже. Больше не хочу видеть ничего подобного.>"
    },
    {
      "id": 2,
      "model": "로쟈",
      "content": "Пф-ф… Грег наверняка рад такое слышать. Я права, жучок?"
    },
    {
      "id": 3,
      "content": "Но Грегор не обращал никакого внимания на Родю."
    },
    {
      "id": 4,
      "model": "그레고르",
      "content": "…Вы не слышите ничего странного?"
    },
    {
      "id": 5,
      "model": "이스마엘",
      "content": "Уже некоторое время слышится бесперебойное урчание. Родион, вам и правда так хочется есть в такое время?"
    },
    {
      "id": 6,
      "model": "로쟈",
      "content": "Э-эй, о таком не нужно говорить вслух~ Хорошо, подружка?"
    },
    {
      "id": 7,
      "model": "그레고르",
      "content": "Нет, я не… Этот звук похож на…"
    },
    {
      "id": 8,
      "content": "Впервые с начала экспедиции Грегор пошёл вперёд группы, после чего открыл стоящую перед собой дверь, будто ведомый потусторонними силами."
    },
    {
      "id": 9,
      "model": "유리",
      "teller": "Юри",
      "title": "Корректировщик\n8-го ранга",
      "content": "Стойте, вы открываете камеру содержания!‥"
    },
    {
      "id": 10,
      "model": "그레고르",
      "content": "Это похоже… на тот раз…"
    },
    {
      "id": 11,
      "content": "Нет, дверь уже была открыта."
    },
    {
      "id": 12,
      "content": "Грегор уставился на дождь из золотых лучей, что лился из пределов комнаты."
    },
    {
      "id": 13,
      "model": "단테",
      "content": "<Гре—!>"
    },
    {
      "id": 14,
      "model": "이스마엘",
      "content": "Мы… переместились назад во времени?"
    },
    {
      "id": 15,
      "content": "Я вижу полностью застланное тучами небо."
    },
    {
      "id": 16,
      "content": "Издалека слышны пронзительные крики и стоны."
    },
    {
      "id": 17,
      "content": "По ушам бьёт какофония из пулемётных очередей и разрывов артиллерийских снарядов."
    },
    {
      "id": 18,
      "model": "오티스",
      "content": "Вы всё ещё не поняли? Это…"
    },
    {
      "id": 19,
      "place": "Посреди Дымной войны",
      "model": "오티스",
      "content": "Поле боя… Его самое сердце."
    },
    {
      "id": 20,
      "model": "그레고르",
      "content": "…Я-я… с-сплю? Это кошмар? П-почему я снова здесь…"
    },
    {
      "id": 21,
      "model": "히스클리프",
      "content": "Так почему мы оказались в центре чёртовой войны?! Это какая-то ловушка?"
    },
    {
      "id": 22,
      "model": "파우스트",
      "content": "Нет. Мы на верном пути."
    },
    {
      "id": 23,
      "model": "파우스트",
      "content": "Эссенция технологий, которую мы пытаемся отыскать, находится недалеко от нас."
    },
    {
      "id": 24,
      "model": "이스마엘",
      "content": "Вы о Золотой ветви?"
    },
    {
      "id": 25,
      "model": "파우스트",
      "content": "Верно. Вам известно, в какой период войны мы переместились?"
    },
    {
      "id": 26,
      "model": "오티스",
      "content": "Любой, у кого ещё остались глаза, поймёт с первого взгляда."
    },
    {
      "id": 27,
      "model": "단테",
      "content": "<Эм-м, я… я не знаю.>"
    },
    {
      "id": 28,
      "content": "Чистосердечное признание."
    },
    {
      "id": 29,
      "model": "오티스",
      "content": "Очевидно, что вы не можете этого знать, директор. У вас нет глаз, которые могли бы ранее упомянутым данным требованиям."
    },
    {
      "id": 30,
      "model": "이스마엘",
      "content": "Вы могли бы придумать оправдание и получше…"
    },
    {
      "id": 31,
      "content": "Утис прокашлялась, чтобы скрыть свой стыд, после чего внимательно оглядела поле боя."
    },
    {
      "id": 32,
      "model": "오티스",
      "content": "Судя по размахам броских знамён, что указывают на стороны в бою…"
    },
    {
      "id": 33,
      "model": "오티스",
      "content": "Прошло как минимум 70 дней с начала войны…"
    },
    {
      "id": 34,
      "model": "오티스",
      "content": "…Это всё, что я могу сказать, директор."
    },
    {
      "id": 35,
      "content": "Вдруг кто-то с напором потянул за рубашку Хитклифа."
    },
    {
      "id": 36,
      "teller": "???",
      "title": "???",
      "content": "Вы совсем с ума сошли? Идите в убежище, сейчас же! Если вас заденет взрывом бомбы, то вы в один миг превратитесь в стариков!"
    },
    {
      "id": 37,
      "teller": "???",
      "title": "???",
      "content": "Соседний от нашего сторожевой пост превратился в дом для престарелых – там никто не может даже ходить без костылей!"
    },
    {
      "id": 38,
      "model": "히스클리프",
      "content": "Кто ты и почему ведёшь себя так, будто мы старые знакомые—"
    },
    {
      "id": 39,
      "teller": "???",
      "title": "???",
      "content": "О! Директор Грегор! Для меня честь встретиться с вами, сэр!"
    },
    {
      "id": 40,
      "content": "Забинтованный парень выпрямился и отдал Грегору честь сразу же, как его заприметил."
    },
    {
      "id": 41,
      "model": "그레고르",
      "content": "…Ты."
    },
    {
      "id": 42,
      "teller": "Тома",
      "title": "Солдат из воспоминаний",
      "content": "Вы меня не знаете, сэр. Я Тома из отдела биомиметического обслуживания!"
    },
    {
      "id": 43,
      "teller": "Тома",
      "title": "Солдат из воспоминаний",
      "content": "Я думал, что вы являетесь частью штурмового отряда. Неожиданно встретить вас здесь в тылу."
    },
    {
      "id": 44,
      "teller": "Тома",
      "title": "Солдат из воспоминаний",
      "content": "Вы выдвигаетесь обратно на фронт? Я могу помочь вам с этим, поскольку мои биоаугментированные ноги позволяет мне прыгать―"
    },
    {
      "id": 45,
      "model": "로쟈",
      "content": "Фу, как же противно звучит."
    },
    {
      "id": 46,
      "content": "Тома с подозрением посмотрел на Родю."
    },
    {
      "id": 47,
      "teller": "Тома",
      "title": "Солдат из воспоминаний",
      "content": "Ты, что ты сейчас…"
    },
    {
      "id": 48,
      "model": "그레고르",
      "content": "Э-эй, Тома! Так ты помощник командира или рядовой солдат?"
    },
    {
      "id": 49,
      "teller": "Тома",
      "title": "Солдат из воспоминаний",
      "content": "Так точно, сэр! Я личный помощник, сэр!"
    },
    {
      "id": 50,
      "model": "그레고르",
      "content": "Ах, видишь ли, она новобранец и лишь недавно прошла операцию, так что… Она всё ещё адаптируется. Я проведу с ней профилактическую беседу."
    },
    {
      "id": 51,
      "teller": "Тома",
      "title": "Солдат из воспоминаний",
      "content": "Ах, вот оно как… Должно быть, наша корпорация становится всё более отчаянной, раз отправляет в бой таких неподготовленных бойцов."
    },
    {
      "id": 52,
      "model": "그레고르",
      "content": "Да, извини за лишние проблемы. Мне нужно её срочно кое-куда отвести…"
    },
    {
      "id": 53,
      "content": "Грегор почти насильно вырвался из разговора и в спешке направился в сторону Фауст."
    },
    {
      "id": 54,
      "model": "그레고르",
      "content": "Что происходит, Фауст? Это…"
    },
    {
      "id": 55,
      "model": "그레고르",
      "content": "…мои воспоминания."
    },
    {
      "id": 56,
      "model": "파우스트",
      "content": "Если точнее, то мы находимся в глубине вашего эго."
    },
    {
      "id": 57,
      "model": "파우스트",
      "content": "Другими словами, это открытый путь к вашему подсознанию…"
    },
    {
      "id": 58,
      "model": "파우스트",
      "content": "Мы ступили в ваше сердце и разум, Грегор."
    }
  ]
}