{
  "dataList": [
    {
      "id": "836601_succeed_1",
      "content": "Защита от физического воздействия активирована"
    },
    {
      "id": "836601_failed_1",
      "content": "Защита от физического воздействия активирована"
    },
    {
      "id": "836602_1_1",
      "content": "Все союзники <color=#00ff9c>восстановили 30 ОЗ</color>"
    },
    {
      "id": "836602_2_1",
      "content": "Все союзники <color=#80c9ff>восстановили 30 ОР</color>"
    },
    {
      "id": "836602_3_1",
      "content": "Все союзники <color=#00ff9c>восстанавливают 3 ОЗ каждый ход</color>"
    },
    {
      "id": "836602_3_2",
      "content": "Все союзники <color=#80c9ff>восстанавливают 3 ОР каждый ход</color>"
    }
  ]
}