{
  "dataList": [
    {
      "id": 0,
      "place": "Фантастический кровострелковый тир",
      "model": "라만차내레이션",
      "teller": "Ведущий",
      "title": "Ламанчаленд",
      "content": "Итак, все плохие Кроводемоны, что жаждали навредить людям, были загнаны под землю."
    },
    {
      "id": 1,
      "model": "라만차내레이션",
      "teller": "Ведущий",
      "title": "Ламанчаленд",
      "content": "На поверхности остались только добросердечные, праведные Кроводемоны."
    },
    {
      "id": 2,
      "model": "라만차내레이션",
      "teller": "Ведущий",
      "title": "Ламанчаленд",
      "content": "Они дали людям честное-пречестное слово, что больше не будут жаждать их крови! Что будут жить вместе мирно и счастливо! Ведь нет ничего лучше мира!"
    },
    {
      "id": 3,
      "model": "라만차내레이션",
      "teller": "Ведущий",
      "title": "Ламанчаленд",
      "content": "О-ох?.. Но вы только посмотрите!"
    },
    {
      "id": 4,
      "model": "라만차내레이션",
      "teller": "Ведущий",
      "title": "Ламанчаленд",
      "content": "Плохие, испорченные Кроводемоны вновь выползают на поверхность!"
    },
    {
      "id": 5,
      "model": "라만차내레이션",
      "teller": "Ведущий",
      "title": "Ламанчаленд",
      "content": "Дабы тайком пить людскую кровушку!"
    }
  ]
}